[
  {
    "title": "Iconic Polish teen novel published in English",
    "published": "Wed, 11 Dec 2024 11:02:59 -0000",
    "link": "https://www.polskieradio.pl/395/7791/Artykul/3456780,iconic-polish-teen-novel-published-in-english",
    "description": "Iconic Polish teen novel published in English",
    "original_date": "2024-12-11T11:02:59+00:00",
    "translated_at": "2024-12-11T18:45:22.950103+00:00"
  },
  {
    "title": "Olga Tokarczuk attends 2024 Nobel Prize ceremony as special guest",
    "published": "Wed, 11 Dec 2024 10:47:59 -0000",
    "link": "https://www.polskieradio.pl/395/7791/Artykul/3457545,olga-tokarczuk-attends-2024-nobel-prize-ceremony-as-special-guest",
    "description": "Olga Tokarczuk attends 2024 Nobel Prize ceremony as special guest",
    "original_date": "2024-12-11T10:47:59+00:00",
    "translated_at": "2024-12-11T18:45:25.182178+00:00"
  },
  {
    "title": "Polish tenor Piotr Beczała shines at Carnegie Hall",
    "published": "Wed, 11 Dec 2024 00:31:13 -0000",
    "link": "https://www.polskieradio.pl/395/7791/Artykul/3456781,polish-tenor-piotr-beczala-shines-at-carnegie-hall",
    "description": "Polish tenor Piotr Beczała shines at Carnegie Hall",
    "original_date": "2024-12-11T00:31:13+00:00",
    "translated_at": "2024-12-11T18:45:27.403126+00:00"
  },
  {
    "title": "European Commission approves 9.4 billion euros for Poland",
    "published": "Wed, 11 Dec 2024 13:06:48 -0000",
    "link": "https://www.polskieradio.pl/395/7786/Artykul/3457621,european-commission-approves-94-billion-euros-for-poland",
    "description": "European Commission approves 9.4 billion euros for Poland",
    "original_date": "2024-12-11T13:06:48+00:00",
    "translated_at": "2024-12-11T18:45:21.150964+00:00"
  },
  {
    "title": "Poland launches second RoPax ferry as government vows to restore Baltic dominance",
    "published": "Wed, 11 Dec 2024 12:51:48 -0000",
    "link": "https://www.polskieradio.pl/395/7786/Artykul/3457622,poland-launches-second-ropax-ferry-as-government-vows-to-restore-baltic-dominance",
    "description": "Poland launches second RoPax ferry as government vows to restore Baltic dominance",
    "original_date": "2024-12-11T12:51:48+00:00",
    "translated_at": "2024-12-11T18:45:23.394175+00:00"
  },
  {
    "title": "UPDATE: Polish billionaire Zygmunt Solorz denies court-imposed asset freeze",
    "published": "Wed, 11 Dec 2024 10:39:40 -0000",
    "link": "https://www.polskieradio.pl/395/7784/Artykul/3456815,update-polish-billionaire-zygmunt-solorz-denies-courtimposed-asset-freeze",
    "description": "UPDATE: Polish billionaire Zygmunt Solorz denies court-imposed asset freeze",
    "original_date": "2024-12-11T10:39:40+00:00",
    "translated_at": "2024-12-11T18:45:25.612349+00:00"
  },
  {
    "title": "Polish president signs bill to freeze electricity prices",
    "published": "Tue, 10 Dec 2024 22:25:10 -0000",
    "link": "https://www.polskieradio.pl/395/7786/Artykul/3456717,polish-president-signs-bill-to-freeze-electricity-prices",
    "description": "Polish president signs bill to freeze electricity prices",
    "original_date": "2024-12-10T22:25:10+00:00",
    "translated_at": "2024-12-11T18:45:27.824990+00:00"
  },
  {
    "title": "Santa on the Kremlin’s naughty list? Russian activist wants Santa Claus labeled a “foreign agent”",
    "published": "Wed, 11 Dec 2024 16:48:32 -0000",
    "link": "https://www.polskieradio.pl/395/7785/Artykul/3457858,santa-on-the-kremlin%E2%80%99s-naughty-list-russian-activist-wants-santa-claus-labeled-a-%E2%80%9Cforeign-agent",
    "description": "Santa on the Kremlin’s naughty list? Russian activist wants Santa Claus labeled a “foreign agent”",
    "original_date": "2024-12-11T16:48:32+00:00",
    "translated_at": "2024-12-11T18:45:23.037785+00:00"
  },
  {
    "title": "Polish, Estonian PMs discuss security, regional issues",
    "published": "Wed, 11 Dec 2024 16:33:32 -0000",
    "link": "https://www.polskieradio.pl/395/7785/Artykul/3457652,polish-estonian-pms-discuss-security-regional-issues",
    "description": "Polish, Estonian PMs discuss security, regional issues",
    "original_date": "2024-12-11T16:33:32+00:00",
    "translated_at": "2024-12-11T18:45:25.302385+00:00"
  },
  {
    "title": "Poland to send diplomatic note over destruction of WWII memorials in Russia",
    "published": "Wed, 11 Dec 2024 09:29:24 -0000",
    "link": "https://www.polskieradio.pl/395/7785/Artykul/3456898,poland-to-send-diplomatic-note-over-destruction-of-wwii-memorials-in-russia",
    "description": "Poland to send diplomatic note over destruction of WWII memorials in Russia",
    "original_date": "2024-12-11T09:29:24+00:00",
    "translated_at": "2024-12-11T18:45:27.509945+00:00"
  },
  {
    "title": "Q and A with Taoufik Chebbi",
    "published": "Tue, 10 Dec 2024 21:42:00 -0000",
    "link": "https://www.polskieradio.pl/395/7991/Artykul/3455139,q-and-a-with-taoufik-chebbi",
    "description": "Q and A with Taoufik Chebbi",
    "original_date": "2024-12-10T21:42:00+00:00",
    "translated_at": "2024-12-11T18:45:30.796022+00:00"
  },
  {
    "title": "Giorgia Meloni named Europe’s most powerful person for 2025 by Politico",
    "published": "Wed, 11 Dec 2024 14:38:21 -0000",
    "link": "https://www.polskieradio.pl/395/7789/Artykul/3457669,giorgia-meloni-named-europe%E2%80%99s-most-powerful-person-for-2025-by-politico",
    "description": "Giorgia Meloni named Europe’s most powerful person for 2025 by Politico",
    "original_date": "2024-12-11T14:38:21+00:00",
    "translated_at": "2024-12-11T18:45:30.773488+00:00"
  },
  {
    "title": "Polish PM reacts to sexual abuse case involving son of top politician",
    "published": "Wed, 11 Dec 2024 10:42:16 -0000",
    "link": "https://www.polskieradio.pl/395/7789/Artykul/3457074,polish-pm-reacts-to-sexual-abuse-case-involving-son-of-top-politician",
    "description": "Polish PM reacts to sexual abuse case involving son of top politician",
    "original_date": "2024-12-11T10:42:16+00:00",
    "translated_at": "2024-12-11T18:45:32.983449+00:00"
  },
  {
    "title": "TVN and Polsat on the list of entities subject to state protection",
    "published": "Wed, 11 Dec 2024 14:58:31 -0000",
    "link": "https://www.polskieradio.pl/399/7976/Artykul/3457600,tvn-i-polsat-na-liscie-podmiotow-podlegajacych-panstwowej-ochronie",
    "description": "TVN and Polsat on the list of entities subject to state protection",
    "original_date": "2024-12-11T14:58:31+00:00",
    "translated_at": "2024-12-11T18:45:37.449161+00:00"
  },
  {
    "title": "Sigma\" named Poland's 2024 Youth Word of the Year",
    "published": "Wed, 11 Dec 2024 12:25:06 -0000",
    "link": "https://www.polskieradio.pl/395/7789/Artykul/3457585,sigma-named-polands-2024-youth-word-of-the-year",
    "description": "Sigma\" named Poland's 2024 Youth Word of the Year",
    "original_date": "2024-12-11T12:25:06+00:00",
    "translated_at": "2024-12-11T18:45:30.323639+00:00"
  },
  {
    "title": "Poland’s 2025 EU presidency to focus on ‘seven dimensions of European security’",
    "published": "Wed, 11 Dec 2024 09:52:04 -0000",
    "link": "https://www.polskieradio.pl/395/7784/Artykul/3457055,poland%E2%80%99s-2025-eu-presidency-to-focus-on-%E2%80%98seven-dimensions-of-european-security%E2%80%99",
    "description": "Poland’s 2025 EU presidency to focus on ‘seven dimensions of European security’",
    "original_date": "2024-12-11T09:52:04+00:00",
    "translated_at": "2024-12-11T18:45:32.516247+00:00"
  },
  {
    "title": "Polish PM reacts to sexual abuse case involving son of top politician",
    "published": "Wed, 11 Dec 2024 09:37:04 -0000",
    "link": "https://www.polskieradio.pl/395/7789/Artykul/3457074,polish-pm-reacts-to-sexual-abuse-case-involving-son-of-top-politician",
    "description": "Polish PM reacts to sexual abuse case involving son of top politician",
    "original_date": "2024-12-11T09:37:04+00:00",
    "translated_at": "2024-12-11T18:45:34.789526+00:00"
  },
  {
    "title": "Polish heroes honored posthumously for saving Jews during WWII",
    "published": "Wed, 11 Dec 2024 09:22:04 -0000",
    "link": "https://www.polskieradio.pl/395/7784/Artykul/3456904,polish-heroes-honored-posthumously-for-saving-jews-during-wwii",
    "description": "Polish heroes honored posthumously for saving Jews during WWII",
    "original_date": "2024-12-11T09:22:04+00:00",
    "translated_at": "2024-12-11T18:45:37.017416+00:00"
  },
  {
    "title": "Polish ex-deputy justice minister faces pretrial detention on corruption charges",
    "published": "Tue, 10 Dec 2024 23:05:26 -0000",
    "link": "https://www.polskieradio.pl/395/7784/Artykul/3456771,polish-exdeputy-justice-minister-faces-pretrial-detention-on-corruption-charges",
    "description": "Polish ex-deputy justice minister faces pretrial detention on corruption charges",
    "original_date": "2024-12-10T23:05:26+00:00",
    "translated_at": "2024-12-11T18:45:39.276885+00:00"
  }
]